cosmicray_rocketchat-0.0.3.dist-info/DESCRIPTION.rst
cosmicray_rocketchat-0.0.3.dist-info/METADATA
cosmicray_rocketchat-0.0.3.dist-info/RECORD
cosmicray_rocketchat-0.0.3.dist-info/WHEEL
cosmicray_rocketchat-0.0.3.dist-info/entry_points.txt
cosmicray_rocketchat-0.0.3.dist-info/metadata.json
cosmicray_rocketchat-0.0.3.dist-info/top_level.txt
rocketchat/__init__.py
rocketchat/__version__.py
rocketchat/cli.py
rocketchat/models.py
rocketchat/v1.py
