Metadata-Version: 2.0
Name: cosmicray-rocketchat
Version: 0.0.3
Summary: Rocket.Chat API Client
Home-page: UNKNOWN
Author: Samir Omerovic
Author-email: somerovi@gmail.com
License: MIT
Platform: UNKNOWN
Classifier: License :: OSI Approved :: MIT License
Classifier: Programming Language :: Python
Classifier: Programming Language :: Python :: 2.6
Classifier: Programming Language :: Python :: 2.7
Classifier: Programming Language :: Python :: 3
Classifier: Programming Language :: Python :: 3.3
Classifier: Programming Language :: Python :: 3.4
Classifier: Programming Language :: Python :: 3.5
Classifier: Programming Language :: Python :: 3.6
Classifier: Programming Language :: Python :: Implementation :: CPython
Classifier: Programming Language :: Python :: Implementation :: PyPy
Requires-Dist: click (==6.7)
Requires-Dist: cosmicray (>=0.0.9)
Requires-Dist: six (==1.11.0)
